dzidb/__init__.py
dzidb/__main__.py
wda/__init__.py
wda/_proto.py
wda/exceptions.py
wda/requests_usbmux.py
wda/usbmux.py
wda/utils.py
wda/xcui_element_types.py
dzidb-1.2.11.dist-info/LICENSE
dzidb-1.2.11.dist-info/METADATA
dzidb-1.2.11.dist-info/WHEEL
dzidb-1.2.11.dist-info/entry_points.txt
dzidb-1.2.11.dist-info/top_level.txt
dzidb-1.2.11.dist-info/RECORD
