Metadata-Version: 2.1
Name: dzidb
Version: 1.2.11
Summary: A custom adb-like tool
Home-page: https://github.com/yourusername/dzidb
Author: Your Name
Author-email: your.email@example.com
License: MIT License
